bakong_khqr/__init__.py
bakong_khqr/khqr.py
bakong_khqr/sdk/__init__.py
bakong_khqr/sdk/additional_data_field.py
bakong_khqr/sdk/amount.py
bakong_khqr/sdk/country_code.py
bakong_khqr/sdk/crc.py
bakong_khqr/sdk/emv.py
bakong_khqr/sdk/emv_parser.py
bakong_khqr/sdk/global_unique_identifier.py
bakong_khqr/sdk/hash.py
bakong_khqr/sdk/image_tools.py
bakong_khqr/sdk/mcc.py
bakong_khqr/sdk/merchant_city.py
bakong_khqr/sdk/merchant_name.py
bakong_khqr/sdk/payload_format_indicator.py
bakong_khqr/sdk/point_of_initiation.py
bakong_khqr/sdk/timestamp.py
bakong_khqr/sdk/transaction_currency.py
bakong_khqr/sdk/version.py
bakong_khqr/sdk/assets/KHR.png
bakong_khqr/sdk/assets/USD.png
bakong_khqr/sdk/assets/bold.ttf
bakong_khqr/sdk/assets/khqr.png
bakong_khqr/sdk/assets/logo.png
bakong_khqr/sdk/assets/regular.ttf
bakong_khqr-0.5.1.dist-info/licenses/LICENSE
bakong_khqr-0.5.1.dist-info/METADATA
bakong_khqr-0.5.1.dist-info/WHEEL
bakong_khqr-0.5.1.dist-info/top_level.txt
bakong_khqr-0.5.1.dist-info/RECORD
