Metadata-Version: 2.4
Name: bakong-khqr
Version: 0.5.1
Summary: A Python package for generating payment transactions compliant with the Bakong KHQR standard. (Unofficial NBC)
Home-page: https://github.com/bsthen/bakong-khqr
Author: BAN Sothen
Author-email: bansokthen@gmail.com
Project-URL: Documentation, https://github.com/bsthen/bakong-khqr#readme
Project-URL: Source, https://github.com/bsthen/bakong-khqr
Project-URL: Tracker, https://github.com/bsthen/bakong-khqr/issues
Classifier: Programming Language :: Python :: 3
Classifier: License :: OSI Approved :: MIT License
Classifier: Operating System :: OS Independent
Requires-Python: >=3.6
License-File: LICENSE
Provides-Extra: image
Requires-Dist: pillow; extra == "image"
Requires-Dist: qrcode; extra == "image"
Dynamic: author
Dynamic: author-email
Dynamic: classifier
Dynamic: description
Dynamic: description-content-type
Dynamic: home-page
Dynamic: license-file
Dynamic: project-url
Dynamic: provides-extra
Dynamic: requires-python
Dynamic: summary
